MANIFEST.in
README.md
setup.py
IVisual_alt.egg-info/PKG-INFO
IVisual_alt.egg-info/SOURCES.txt
IVisual_alt.egg-info/dependency_links.txt
IVisual_alt.egg-info/not-zip-safe
IVisual_alt.egg-info/requires.txt
IVisual_alt.egg-info/top_level.txt
ivisual/__init__.py
ivisual/crayola.py
ivisual/materials.py
ivisual/rate_control.py
ivisual/visual.py
ivisual/data/glow.1.1.min.js
ivisual/data/glowcomm.js
ivisual/data/jquery-ui.custom.min.js
ivisual/test/__init__.py
ivisual/test/test_crayola.py
ivisual/test/test_materials.py
ivisual/test/test_rate_control.py
ivisual/test/test_visual.py