Metadata-Version: 1.1
Name: IVisual-alt
Version: 0.2.3
Summary: VPython visual inline for IPython Notebook
Home-page: https://github.com/nwhitehead/IVisual
Author: John Coady, Nathan Whitehead
Author-email: johncoady@shaw.ca, nwhitehe@gmail.com
License: Unknown
Keywords: VPython,IPython,IVisual,jupyter,notebook,Graphics,3D,visualization,rendering,animation
Platform: UNKNOWN
Classifier: Framework :: IPython
Classifier: Development Status :: 4 - Beta
Classifier: Environment :: Web Environment
Classifier: Intended Audience :: End Users/Desktop
Classifier: Natural Language :: English
Classifier: Programming Language :: Python :: 2.7
Classifier: Topic :: Multimedia :: Graphics :: 3D Modeling
Classifier: Topic :: Multimedia :: Graphics :: 3D Rendering
Classifier: Topic :: Scientific/Engineering :: Visualization
